{
  "modid": ["chisel", "fossil"],
  "blocks": [
    {
      "from": {
        "block": "fossil:palm_planks"
      },
      "mode": "plank",
      "through": {
        "block": "chisel:planks-oak",
        "iterate": [
          "variation"
        ]
      },
      "based_upon": {
        "state": "minecraft:planks#variant=oak"
      }
    },
    {
      "from": {
        "block": "fossil:calamites_planks"
      },
      "mode": "plank",
      "through": {
        "block": "chisel:planks-oak",
        "iterate": [
          "variation"
        ]
      },
      "based_upon": {
        "state": "minecraft:planks#variant=oak"
      }
    },
    {
      "from": {
        "block": "fossil:cordaites_planks"
      },
      "mode": "plank",
      "through": {
        "block": "chisel:planks-oak",
        "iterate": [
          "variation"
        ]
      },
      "based_upon": {
        "state": "minecraft:planks#variant=oak"
      }
    },
    {
      "from": {
        "block": "fossil:ancient_stone_brick"
      },
      "through": {
        "block": "chisel:stonebrick",
        "iterate": [
          "variation"
        ]
      },
      "based_upon": {
        "state": "minecraft:stonebrick#variant=stonebrick"
      }
    },
    {
      "from": {
        "block": "fossil:ancient_stone_brick"
      },
      "through": {
        "block": "chisel:stonebrick1",
        "iterate": [
          "variation"
        ]
      },
      "based_upon": {
        "state": "minecraft:stonebrick#variant=stonebrick"
      }
    },
    {
      "from": {
        "block": "fossil:ancient_stone_brick"
      },
      "through": {
        "block": "chisel:stonebrick2",
        "iterate": [
          "variation"
        ]
      },
      "based_upon": {
        "state": "minecraft:stonebrick#variant=stonebrick"
      }
    },
    {
      "from": {
        "block": "fossil:volcanic_brick"
      },
      "through": {
        "block": "chisel:stonebrick",
        "iterate": [
          "variation"
        ]
      },
      "based_upon": {
        "state": "minecraft:stonebrick#variant=stonebrick"
      }
    },
    {
      "from": {
        "block": "fossil:volcanic_brick"
      },
      "through": {
        "block": "chisel:stonebrick1",
        "iterate": [
          "variation"
        ]
      },
      "based_upon": {
        "state": "minecraft:stonebrick#variant=stonebrick"
      }
    },
    {
      "from": {
        "block": "fossil:volcanic_brick"
      },
      "through": {
        "block": "chisel:stonebrick2",
        "iterate": [
          "variation"
        ]
      },
      "based_upon": {
        "state": "minecraft:stonebrick#variant=stonebrick"
      }
    }
  ]
}
